.gitignore
README.rst
setup.cfg
setup.py
mr.rubber.egg-info/PKG-INFO
mr.rubber.egg-info/SOURCES.txt
mr.rubber.egg-info/dependency_links.txt
mr.rubber.egg-info/entry_points.txt
mr.rubber.egg-info/not-zip-safe
mr.rubber.egg-info/requires.txt
mr.rubber.egg-info/top_level.txt
mrrubber/__init__.py
mrrubber/rubber.py
mrrubber/tests.py