Metadata-Version: 1.0
Name: mr.rubber
Version: 1.0dev
Summary: your elastic friend to start supervisord processes based on cpu cores available
Home-page: http://pypi.python.org/pypi/mr.rubber
Author: Dylan Jay
Author-email: software@pretaweb.com
License: GPL
Keywords: supervisord
Platform: UNKNOWN
